netbox_graylog/__init__.py
netbox_graylog/forms.py
netbox_graylog/graylog_client.py
netbox_graylog/navigation.py
netbox_graylog/urls.py
netbox_graylog/views.py
netbox_graylog/templates/netbox_graylog/logs_tab.html
netbox_graylog/templates/netbox_graylog/settings.html
netbox_graylog-1.1.0.dist-info/licenses/LICENSE
netbox_graylog-1.1.0.dist-info/METADATA
netbox_graylog-1.1.0.dist-info/WHEEL
netbox_graylog-1.1.0.dist-info/top_level.txt
netbox_graylog-1.1.0.dist-info/RECORD
