Metadata-Version: 2.4
Name: netbox-graylog
Version: 1.1.0
Summary: NetBox plugin to display Graylog logs in device and VM detail pages
Author-email: sieteunoseis <jeremy.worden@gmail.com>
License: Apache-2.0
Project-URL: Homepage, https://github.com/sieteunoseis/netbox-graylog
Project-URL: Repository, https://github.com/sieteunoseis/netbox-graylog
Project-URL: Issues, https://github.com/sieteunoseis/netbox-graylog/issues
Keywords: netbox,graylog,logging,plugin
Classifier: Development Status :: 4 - Beta
Classifier: Framework :: Django
Classifier: Intended Audience :: System Administrators
Classifier: License :: OSI Approved :: Apache Software License
Classifier: Programming Language :: Python :: 3
Classifier: Programming Language :: Python :: 3.10
Classifier: Programming Language :: Python :: 3.11
Classifier: Programming Language :: Python :: 3.12
Requires-Python: >=3.10
License-File: LICENSE
Requires-Dist: requests>=2.28.0
Provides-Extra: dev
Requires-Dist: black; extra == "dev"
Requires-Dist: flake8; extra == "dev"
Requires-Dist: isort; extra == "dev"
Requires-Dist: pytest; extra == "dev"
Dynamic: license-file
